README.md
setup.py
gf_wordnet.egg-info/PKG-INFO
gf_wordnet.egg-info/SOURCES.txt
gf_wordnet.egg-info/dependency_links.txt
gf_wordnet.egg-info/not-zip-safe
gf_wordnet.egg-info/requires.txt
gf_wordnet.egg-info/top_level.txt
wordnet/__init__.py
wordnet/_api.py
wordnet/_semantics.py