Metadata-Version: 2.1
Name: gf-wordnet
Version: 0.0.14
Summary: An API to the GF WordNet.
Home-page: https://github.com/GrammaticalFramework/gf-wordnet
Author: Krasimir Angelov
Author-email: kr.angelov@gmail.com
License: BSD
Keywords: GF WordNet
Requires-Dist: pgf-majestic
Requires-Dist: daison
